MANIFEST.in
README.rst
setup.cfg
setup.py
django_netbox_confluence/__init__.py
django_netbox_confluence/admin.py
django_netbox_confluence/apps.py
django_netbox_confluence/auth.py
django_netbox_confluence/models.py
django_netbox_confluence/tests.py
django_netbox_confluence/urls.py
django_netbox_confluence/views.py
django_netbox_confluence.egg-info/PKG-INFO
django_netbox_confluence.egg-info/SOURCES.txt
django_netbox_confluence.egg-info/dependency_links.txt
django_netbox_confluence.egg-info/requires.txt
django_netbox_confluence.egg-info/top_level.txt
django_netbox_confluence/migrations/0001_initial.py
django_netbox_confluence/migrations/__init__.py
django_netbox_confluence/templates/multiexcerpt.xml
django_netbox_confluence/templates/wrapper.xml
django_netbox_confluence/updater/__init__.py
django_netbox_confluence/updater/confluence_adapter.py
django_netbox_confluence/updater/exceptioins.py
django_netbox_confluence/updater/linked_fields.py
django_netbox_confluence/updater/wiki_updater.py
docs/dnc_config.png
docs/netbox_config.png